ecb/__init__.py
ecb/ipc.py
ecb/structs.py
ecb/uds.py
ecb/util.py
ecb-0.1.1.dist-info/METADATA
ecb-0.1.1.dist-info/WHEEL
ecb-0.1.1.dist-info/top_level.txt
ecb-0.1.1.dist-info/RECORD
